uiutils/__init__.py
uiutils/gridview.py
uiutils/hierarchy.py
uiutils/menu.py
uiutils/richlabel.py
uiutils/safearea.py
uiutils/sfsymbol.py
pythonista_uiutils-2020.10.28.dist-info/WHEEL
pythonista_uiutils-2020.10.28.dist-info/METADATA
pythonista_uiutils-2020.10.28.dist-info/RECORD
