Metadata-Version: 2.1
Name: pythonista-uiutils
Version: 2020.10.28
Summary: UI and other utils for Pythonista iOS app
Home-page: https://github.com/mikaelho/uiutils
License: TheUnlicense
Author: Mikael Honkala
Author-email: mikael.honkala@gmail.com
Classifier: Operating System :: iOS
